<odoo>
  <data>
    <!-- explicit list view definition -->
    <!--
    <record model="ir.ui.view" id="pos_item_count.list">
      <field name="name">pos_item_count list</field>
      <field name="model">pos_item_count.pos_item_count</field>
      <field name="arch" type="xml">
        <tree>
          <field name="name"/>
          <field name="value"/>
          <field name="value2"/>
        </tree>
      </field>
    </record>
    -->

    <!-- actions opening views on models -->
    <!--
    <record model="ir.actions.act_window" id="pos_item_count.action_window">
      <field name="name">pos_item_count window</field>
      <field name="res_model">pos_item_count.pos_item_count</field>
      <field name="view_mode">tree,form</field>
    </record>
    -->

    <!-- server action to the one above -->
    <!--
    <record model="ir.actions.server" id="pos_item_count.action_server">
      <field name="name">pos_item_count server</field>
      <field name="model_id" ref="model_pos_item_count_pos_item_count"/>
      <field name="code">
        action = {
          "type": "ir.actions.act_window",
          "view_mode": "tree,form",
          "res_model": self._name,
        }
      </field>
    </record>
    -->

    <!-- Top menu item -->
    <!--
    <menuitem name="pos_item_count" id="pos_item_count.menu_root"/>
    -->
    <!-- menu categories -->
    <!--
    <menuitem name="Menu 1" id="pos_item_count.menu_1" parent="pos_item_count.menu_root"/>
    <menuitem name="Menu 2" id="pos_item_count.menu_2" parent="pos_item_count.menu_root"/>
    -->
    <!-- actions -->
    <!--
    <menuitem name="List" id="pos_item_count.menu_1_list" parent="pos_item_count.menu_1"
              action="pos_item_count.action_window"/>
    <menuitem name="Server to list" id="pos_item_count" parent="pos_item_count.menu_2"
              action="pos_item_count.action_server"/>
    -->
  </data>
</odoo>